setup.py
django_tekextensions.egg-info/PKG-INFO
django_tekextensions.egg-info/SOURCES.txt
django_tekextensions.egg-info/dependency_links.txt
django_tekextensions.egg-info/top_level.txt
tekextensions/__init__.py
tekextensions/context_processors.py
tekextensions/models.py
tekextensions/tests.py
tekextensions/views.py
tekextensions/widgets.py