Metadata-Version: 1.0
Name: django-tekextensions
Version: 0.0.2
Summary: A set of re-usable widgets and commands for django
Home-page: http://github.com/sontek/django-tekextensions
Author: John Anderson
Author-email: sontek@gmail.com
License: BSD
Download-URL: http://github.com/sontek/django-tekextensions
Platform: UNKNOWN
Classifier: Framework :: Django
Classifier: License :: OSI Approved :: BSD License
Classifier: Operating System :: OS Independent
Classifier: Programming Language :: Python
